lapa_commons/__init__.py
lapa_commons/main.py
lapa_commons-0.0.3.dist-info/METADATA
lapa_commons-0.0.3.dist-info/WHEEL
lapa_commons-0.0.3.dist-info/top_level.txt
lapa_commons-0.0.3.dist-info/RECORD
