Metadata-Version: 2.1
Name: lapa-commons
Version: 0.0.3
Summary: Lapa commons used for reading the configuration file.
Home-page: https://github.com/B21amish/lapa_commons
Author: Lav Sharma, thePmSquare
Author-email: lavsharma2016@gmail.com, thepmsquare@gmail.com
License: UNKNOWN
Platform: UNKNOWN
Classifier: Development Status :: 3 - Alpha
Classifier: Intended Audience :: Developers
Classifier: License :: OSI Approved :: MIT License
Classifier: Programming Language :: Python :: 3
Classifier: Programming Language :: Python :: 3.9
Requires-Dist: configparser >=6.0.0
